deseq2_wrapper/__init__.py
deseq2_wrapper/deseq2_functions.R
deseq2_wrapper/deseq2_wrapper.py
deseq2_wrapper-0.1.1.dist-info/METADATA
deseq2_wrapper-0.1.1.dist-info/WHEEL
deseq2_wrapper-0.1.1.dist-info/top_level.txt
deseq2_wrapper-0.1.1.dist-info/RECORD
