Metadata-Version: 2.4
Name: deseq2-wrapper
Version: 0.1.1
Summary: Python wrapper for DESeq2 RNA-seq differential expression analysis in Arabidopsis
Home-page: https://github.com/yourusername/deseq2-wrapper
Author: Pai Li, Claude Opus 4
Author-email: lipai@umd.edu
Keywords: RNA-seq,differential expression,DESeq2,bioinformatics,transcriptomics
Classifier: Development Status :: 3 - Alpha
Classifier: Intended Audience :: Science/Research
Classifier: Topic :: Scientific/Engineering :: Bio-Informatics
Classifier: License :: OSI Approved :: MIT License
Classifier: Programming Language :: Python :: 3
Classifier: Programming Language :: Python :: 3.7
Classifier: Programming Language :: Python :: 3.8
Classifier: Programming Language :: Python :: 3.9
Classifier: Programming Language :: Python :: 3.10
Classifier: Programming Language :: Python :: 3.11
Requires-Python: >=3.7
Requires-Dist: pandas>=1.0.0
Requires-Dist: numpy>=1.18.0
Requires-Dist: rpy2>=3.0.0
Requires-Dist: openpyxl>=3.0.0
Dynamic: author
Dynamic: author-email
Dynamic: classifier
Dynamic: description
Dynamic: description-content-type
Dynamic: home-page
Dynamic: keywords
Dynamic: requires-dist
Dynamic: requires-python
Dynamic: summary
